[
  {
    "vote_id": "2026-03-26-RCV-189597",
    "date": "2026-03-26",
    "title": "A10-0048/2026 – Malik Azmani – Decision to enter into interinstitutional negotiations",
    "result": "Adopted",
    "ep_url": "https://www.europarl.europa.eu/doceo/document/PV-10-2026-03-26-RCV_EN.html",
    "position": "for"
  },
  {
    "vote_id": "2026-03-25-RCV-189875",
    "date": "2026-03-25",
    "title": "Wednesday’s agenda – Request by The Left Group – Australia",
    "result": "Rejected",
    "ep_url": "https://www.europarl.europa.eu/doceo/document/PV-10-2026-03-25-RCV_EN.html",
    "position": "for"
  },
  {
    "vote_id": "2026-03-25-RCV-189876",
    "date": "2026-03-25",
    "title": "Wednesday’s agenda – Request by the PPE Group – Iran",
    "result": "Adopted",
    "ep_url": "https://www.europarl.europa.eu/doceo/document/PV-10-2026-03-25-RCV_EN.html",
    "position": "for"
  },
  {
    "vote_id": "2026-03-25-RCV-189877",
    "date": "2026-03-25",
    "title": "Thursday's agenda – Request by the Verts/ALE Group – Request for withdrawal from voting time",
    "result": "Rejected",
    "ep_url": "https://www.europarl.europa.eu/doceo/document/PV-10-2026-03-25-RCV_EN.html",
    "position": "against"
  },
  {
    "vote_id": "2026-03-10-RCV-186885",
    "date": "2026-03-10",
    "title": "A10-0011/2026 – Veronika Cifrová Ostrihoňová – After § 10 – Am 10",
    "result": "Rejected",
    "ep_url": "https://www.europarl.europa.eu/doceo/document/PV-10-2026-03-10-RCV_EN.html",
    "position": "against"
  },
  {
    "vote_id": "2026-03-10-RCV-186887",
    "date": "2026-03-10",
    "title": "A10-0011/2026 – Veronika Cifrová Ostrihoňová – § 26 – Am 11",
    "result": "Rejected",
    "ep_url": "https://www.europarl.europa.eu/doceo/document/PV-10-2026-03-10-RCV_EN.html",
    "position": "against"
  },
  {
    "vote_id": "2026-03-10-RCV-186888",
    "date": "2026-03-10",
    "title": "A10-0011/2026 – Veronika Cifrová Ostrihoňová – After § 27 – Am 12",
    "result": "Rejected",
    "ep_url": "https://www.europarl.europa.eu/doceo/document/PV-10-2026-03-10-RCV_EN.html",
    "position": "against"
  },
  {
    "vote_id": "2026-03-10-RCV-186891",
    "date": "2026-03-10",
    "title": "A10-0011/2026 – Veronika Cifrová Ostrihoňová – After § 32 – Am 13",
    "result": "Rejected",
    "ep_url": "https://www.europarl.europa.eu/doceo/document/PV-10-2026-03-10-RCV_EN.html",
    "position": "against"
  },
  {
    "vote_id": "2026-03-10-RCV-186892",
    "date": "2026-03-10",
    "title": "A10-0011/2026 – Veronika Cifrová Ostrihoňová – After § 37 – Am 14",
    "result": "Rejected",
    "ep_url": "https://www.europarl.europa.eu/doceo/document/PV-10-2026-03-10-RCV_EN.html",
    "position": "against"
  },
  {
    "vote_id": "2026-03-10-RCV-186375",
    "date": "2026-03-10",
    "title": "A10-0011/2026 – Veronika Cifrová Ostrihoňová – Motion for a resolution (as a whole)",
    "result": "Adopted",
    "ep_url": "https://www.europarl.europa.eu/doceo/document/PV-10-2026-03-10-RCV_EN.html",
    "position": "for"
  },
  {
    "vote_id": "2026-03-10-RCV-186169",
    "date": "2026-03-10",
    "title": "A10-0019/2026 – Axel Voss – Motion for a resolution (as a whole)",
    "result": "Adopted",
    "ep_url": "https://www.europarl.europa.eu/doceo/document/PV-10-2026-03-10-RCV_EN.html",
    "position": "for"
  },
  {
    "vote_id": "2026-03-10-RCV-188572",
    "date": "2026-03-10",
    "title": "A10-0018/2026 – André Franqueira Rodrigues – § 8/2",
    "result": "Adopted",
    "ep_url": "https://www.europarl.europa.eu/doceo/document/PV-10-2026-03-10-RCV_EN.html",
    "position": "for"
  },
  {
    "vote_id": "2026-03-10-RCV-188573",
    "date": "2026-03-10",
    "title": "A10-0018/2026 – André Franqueira Rodrigues – § 16 – Am 2",
    "result": "Rejected",
    "ep_url": "https://www.europarl.europa.eu/doceo/document/PV-10-2026-03-10-RCV_EN.html",
    "position": "abstain"
  },
  {
    "vote_id": "2026-03-10-RCV-188574",
    "date": "2026-03-10",
    "title": "A10-0018/2026 – André Franqueira Rodrigues – § 17 – Am 3",
    "result": "Rejected",
    "ep_url": "https://www.europarl.europa.eu/doceo/document/PV-10-2026-03-10-RCV_EN.html",
    "position": "abstain"
  },
  {
    "vote_id": "2026-03-10-RCV-188575",
    "date": "2026-03-10",
    "title": "A10-0018/2026 – André Franqueira Rodrigues – § 18/1",
    "result": "Adopted",
    "ep_url": "https://www.europarl.europa.eu/doceo/document/PV-10-2026-03-10-RCV_EN.html",
    "position": "for"
  },
  {
    "vote_id": "2026-03-10-RCV-188576",
    "date": "2026-03-10",
    "title": "A10-0018/2026 – André Franqueira Rodrigues – After recital Z – Am 1",
    "result": "Adopted",
    "ep_url": "https://www.europarl.europa.eu/doceo/document/PV-10-2026-03-10-RCV_EN.html",
    "position": "abstain"
  },
  {
    "vote_id": "2026-03-10-RCV-186407",
    "date": "2026-03-10",
    "title": "A10-0018/2026 – André Franqueira Rodrigues – Motion for a resolution (as a whole)",
    "result": "Adopted",
    "ep_url": "https://www.europarl.europa.eu/doceo/document/PV-10-2026-03-10-RCV_EN.html",
    "position": "for"
  },
  {
    "vote_id": "2026-03-10-RCV-188553",
    "date": "2026-03-10",
    "title": "B10-0156/2026 – After § 3 – Am 11",
    "result": "Rejected",
    "ep_url": "https://www.europarl.europa.eu/doceo/document/PV-10-2026-03-10-RCV_EN.html",
    "position": "against"
  },
  {
    "vote_id": "2026-03-10-RCV-188554",
    "date": "2026-03-10",
    "title": "B10-0156/2026 – § 4 – Am 1",
    "result": "Rejected",
    "ep_url": "https://www.europarl.europa.eu/doceo/document/PV-10-2026-03-10-RCV_EN.html",
    "position": "for"
  },
  {
    "vote_id": "2026-03-10-RCV-188556",
    "date": "2026-03-10",
    "title": "B10-0156/2026 – After § 4 – Am 12",
    "result": "Rejected",
    "ep_url": "https://www.europarl.europa.eu/doceo/document/PV-10-2026-03-10-RCV_EN.html",
    "position": "against"
  },
  {
    "vote_id": "2026-03-10-RCV-188557",
    "date": "2026-03-10",
    "title": "B10-0156/2026 – After § 4 – Am 15",
    "result": "Rejected",
    "ep_url": "https://www.europarl.europa.eu/doceo/document/PV-10-2026-03-10-RCV_EN.html",
    "position": "against"
  },
  {
    "vote_id": "2026-03-10-RCV-188558",
    "date": "2026-03-10",
    "title": "B10-0156/2026 – § 6",
    "result": "Adopted",
    "ep_url": "https://www.europarl.europa.eu/doceo/document/PV-10-2026-03-10-RCV_EN.html",
    "position": "for"
  },
  {
    "vote_id": "2026-03-10-RCV-188559",
    "date": "2026-03-10",
    "title": "B10-0156/2026 – After § 6 – Am 16",
    "result": "Adopted",
    "ep_url": "https://www.europarl.europa.eu/doceo/document/PV-10-2026-03-10-RCV_EN.html",
    "position": "for"
  },
  {
    "vote_id": "2026-03-10-RCV-188560",
    "date": "2026-03-10",
    "title": "B10-0156/2026 – § 8 – Am 3",
    "result": "Rejected",
    "ep_url": "https://www.europarl.europa.eu/doceo/document/PV-10-2026-03-10-RCV_EN.html",
    "position": "against"
  },
  {
    "vote_id": "2026-03-10-RCV-188562",
    "date": "2026-03-10",
    "title": "B10-0156/2026 – § 11 – Am 4",
    "result": "Rejected",
    "ep_url": "https://www.europarl.europa.eu/doceo/document/PV-10-2026-03-10-RCV_EN.html",
    "position": "for"
  },
  {
    "vote_id": "2026-03-10-RCV-188563",
    "date": "2026-03-10",
    "title": "B10-0156/2026 – After recital A – Am 7",
    "result": "Rejected",
    "ep_url": "https://www.europarl.europa.eu/doceo/document/PV-10-2026-03-10-RCV_EN.html",
    "position": "against"
  },
  {
    "vote_id": "2026-03-10-RCV-188564",
    "date": "2026-03-10",
    "title": "B10-0156/2026 – Motion for a resolution (as a whole)",
    "result": "Adopted",
    "ep_url": "https://www.europarl.europa.eu/doceo/document/PV-10-2026-03-10-RCV_EN.html",
    "position": "for"
  },
  {
    "vote_id": "2026-03-09-RCV-188549",
    "date": "2026-03-09",
    "title": "Tuesday’s agenda – Request by the PfE Group",
    "result": "Rejected",
    "ep_url": "https://www.europarl.europa.eu/doceo/document/PV-10-2026-03-09-RCV_EN.html",
    "position": "for"
  }
]